varvault/__init__.py
varvault/factory.py
varvault/flags.py
varvault/keyring.py
varvault/logger.py
varvault/minivault.py
varvault/resource.py
varvault/subscriber_thread.py
varvault/utils.py
varvault/validator.py
varvault/vault.py
varvault/vaultstructs.py
varvault-6.0.2.dist-info/LICENSE
varvault-6.0.2.dist-info/METADATA
varvault-6.0.2.dist-info/WHEEL
varvault-6.0.2.dist-info/top_level.txt
varvault-6.0.2.dist-info/RECORD
