Metadata-Version: 2.1
Name: varvault
Version: 6.0.2
Summary: A package that sets up a key-value vault to store and access variables in a global context.
Home-page: https://github.com/data-ductus/varvault
Author: Chloe Holst
Author-email: chloe.holst@dataductus.se
License: Apache 2.0
Classifier: License :: OSI Approved :: Apache Software License
Classifier: Programming Language :: Python :: 3
Classifier: Programming Language :: Python :: 3.8
License-File: LICENSE
